guinsoft_ragas/__init__.py
guinsoft_ragas/_analytics.py
guinsoft_ragas/_version.py
guinsoft_ragas/async_utils.py
guinsoft_ragas/evaluation.py
guinsoft_ragas/exceptions.py
guinsoft_ragas/utils.py
guinsoft_ragas/validation.py
guinsoft_ragas/embeddings/__init__.py
guinsoft_ragas/embeddings/base.py
guinsoft_ragas/langchain/__init__.py
guinsoft_ragas/langchain/evalchain.py
guinsoft_ragas/langsmith/__init__.py
guinsoft_ragas/langsmith/evaluator.py
guinsoft_ragas/llama_index/__init__.py
guinsoft_ragas/llama_index/evaluation.py
guinsoft_ragas/llms/__init__.py
guinsoft_ragas/llms/base.py
guinsoft_ragas/llms/langchain.py
guinsoft_ragas/llms/llamaindex.py
guinsoft_ragas/llms/openai.py
guinsoft_ragas/metrics/__init__.py
guinsoft_ragas/metrics/_answer_correctness.py
guinsoft_ragas/metrics/_answer_correctness_bisheng.py
guinsoft_ragas/metrics/_answer_correctness_guinsoft.py
guinsoft_ragas/metrics/_answer_recall_bisheng.py
guinsoft_ragas/metrics/_answer_recall_guinsoft.py
guinsoft_ragas/metrics/_answer_relevance.py
guinsoft_ragas/metrics/_answer_similarity.py
guinsoft_ragas/metrics/_context_precision.py
guinsoft_ragas/metrics/_context_recall.py
guinsoft_ragas/metrics/_context_relevancy.py
guinsoft_ragas/metrics/_faithfulness.py
guinsoft_ragas/metrics/base.py
guinsoft_ragas/metrics/critique.py
guinsoft_ragas/testset/__init__.py
guinsoft_ragas/testset/prompts.py
guinsoft_ragas/testset/testset_generator.py
guinsoft_ragas/testset/utils.py
guinsoft_ragas/trainset/__init__.py
guinsoft_ragas/trainset/prompts.py
guinsoft_ragas/trainset/trainset_generator.py
guinsoft_ragas/trainset/utils.py
guinsoft_rags-1.0.3.dist-info/METADATA
guinsoft_rags-1.0.3.dist-info/WHEEL
guinsoft_rags-1.0.3.dist-info/top_level.txt
guinsoft_rags-1.0.3.dist-info/RECORD
