Metadata-Version: 2.4
Name: guinsoft_rags
Version: 1.0.3
Summary: guinsoft_rags
Author: guinsoft
Requires-Dist: numpy
Requires-Dist: datasets
Requires-Dist: tiktoken
Requires-Dist: langchain
Requires-Dist: openai>1
Requires-Dist: pysbd>=0.3.4
Requires-Dist: nest-asyncio
Requires-Dist: sentence-transformers; extra == "all"
Dynamic: author
Dynamic: description
Dynamic: description-content-type
Dynamic: requires-dist
Dynamic: summary
